mujoco_ar_viewer/__init__.py
mujoco_ar_viewer/upload_xml.py
mujoco_ar_viewer/viewer.py
mujoco_ar_viewer/generated/__init__.py
mujoco_ar_viewer/generated/mujoco_ar_pb2.py
mujoco_ar_viewer/generated/mujoco_ar_pb2_grpc.py
mujoco_ar_viewer-0.4.8.dist-info/licenses/LICENSE
mujoco_ar_viewer-0.4.8.dist-info/METADATA
mujoco_ar_viewer-0.4.8.dist-info/WHEEL
mujoco_ar_viewer-0.4.8.dist-info/top_level.txt
mujoco_ar_viewer-0.4.8.dist-info/RECORD
