Metadata-Version: 2.4
Name: mujoco-ar-viewer
Version: 0.4.8
Summary: AR visualization for MuJoCo physics simulations
Author: Improbable AI
Project-URL: Homepage, https://github.com/Improbable-AI/mujocoARViewer
Project-URL: Repository, https://github.com/Improbable-AI/mujocoARViewer
Project-URL: Issues, https://github.com/Improbable-AI/mujocoARViewer/issues
Keywords: mujoco,ar,vr,visualization,physics,simulation
Classifier: Development Status :: 3 - Alpha
Classifier: Intended Audience :: Developers
Classifier: Intended Audience :: Science/Research
Classifier: Programming Language :: Python :: 3
Classifier: Programming Language :: Python :: 3.8
Classifier: Programming Language :: Python :: 3.9
Classifier: Programming Language :: Python :: 3.10
Classifier: Programming Language :: Python :: 3.11
Classifier: Topic :: Scientific/Engineering :: Artificial Intelligence
Classifier: Topic :: Scientific/Engineering :: Physics
Classifier: Topic :: Scientific/Engineering :: Visualization
Requires-Python: >=3.8
License-File: LICENSE
Requires-Dist: mujoco>=3.1.0
Requires-Dist: grpcio>=1.56.0
Requires-Dist: grpcio-tools>=1.56.0
Requires-Dist: numpy>=1.24.0
Requires-Dist: protobuf>=4.24.0
Requires-Dist: requests
Requires-Dist: python-multipart
Provides-Extra: usd
Requires-Dist: mujoco-usd-converter; extra == "usd"
Dynamic: license-file
